Workbook

Sheet Raw Data
A1: Order ID | B1: Date | C1: Region | D1: Salesperson | E1: Product Category | F1: Product Name | G1: Units Sold | H1: Unit Price (BDT) | I1: Revenue (BDT) | J1: COGS (BDT) | K1: Gross Profit (BDT) | L1: Profit Margin (%)
A2: ORD-001 | B2: 2024-01-05 | C2: Dhaka | D2: Rahim | E2: Electronics | F2: Laptop | G2: 12 | H2: 75000 | I2: =G2*H2 -> 900000 | J2: =I2*0.62 -> 558000 | K2: =I2-J2 -> 342000 | L2: =IF(I2=0,0,K2/I2) -> 0.38
A3: ORD-002 | B3: 2024-01-12 | C3: Chittagong | D3: Fatima | E3: Electronics | F3: Smartphone | G3: 30 | H3: 25000 | I3: =G3*H3 -> 750000 | J3: =I3*0.62 -> 465000 | K3: =I3-J3 -> 285000 | L3: =IF(I3=0,0,K3/I3) -> 0.38
A4: ORD-003 | B4: 2024-01-18 | C4: Sylhet | D4: Karim | E4: Accessories | F4: Headphones | G4: 50 | H4: 3500 | I4: =G4*H4 -> 175000 | J4: =I4*0.45 -> 78750 | K4: =I4-J4 -> 96250 | L4: =IF(I4=0,0,K4/I4) -> 0.55
A5: ORD-004 | B5: 2024-02-02 | C5: Dhaka | D5: Rahim | E5: Software | F5: Antivirus License | G5: 80 | H5: 2200 | I5: =G5*H5 -> 176000 | J5: =I5*0.28 -> 49280 | K5: =I5-J5 -> 126720 | L5: =IF(I5=0,0,K5/I5) -> 0.72
A6: ORD-005 | B6: 2024-02-14 | C6: Rajshahi | D6: Nadia | E6: Electronics | F6: Tablet | G6: 20 | H6: 35000 | I6: =G6*H6 -> 700000 | J6: =I6*0.62 -> 434000 | K6: =I6-J6 -> 266000 | L6: =IF(I6=0,0,K6/I6) -> 0.38
A7: ORD-006 | B7: 2024-02-20 | C7: Chittagong | D7: Fatima | E7: Accessories | F7: USB Hub | G7: 100 | H7: 1200 | I7: =G7*H7 -> 120000 | J7: =I7*0.45 -> 54000 | K7: =I7-J7 -> 66000 | L7: =IF(I7=0,0,K7/I7) -> 0.55
A8: ORD-007 | B8: 2024-03-05 | C8: Dhaka | D8: Karim | E8: Software | F8: Office Suite | G8: 60 | H8: 5500 | I8: =G8*H8 -> 330000 | J8: =I8*0.28 -> 92400 | K8: =I8-J8 -> 237600 | L8: =IF(I8=0,0,K8/I8) -> 0.72
A9: ORD-008 | B9: 2024-03-15 | C9: Sylhet | D9: Rahim | E9: Electronics | F9: Monitor | G9: 15 | H9: 22000 | I9: =G9*H9 -> 330000 | J9: =I9*0.62 -> 204600 | K9: =I9-J9 -> 125400 | L9: =IF(I9=0,0,K9/I9) -> 0.38
A10: ORD-009 | B10: 2024-03-22 | C10: Rajshahi | D10: Nadia | E10: Accessories | F10: Keyboard | G10: 75 | H10: 2800 | I10: =G10*H10 -> 210000 | J10: =I10*0.45 -> 94500 | K10: =I10-J10 -> 115500 | L10: =IF(I10=0,0,K10/I10) -> 0.55
A11: ORD-010 | B11: 2024-04-08 | C11: Dhaka | D11: Fatima | E11: Electronics | F11: Laptop | G11: 8 | H11: 75000 | I11: =G11*H11 -> 600000 | J11: =I11*0.62 -> 372000 | K11: =I11-J11 -> 228000 | L11: =IF(I11=0,0,K11/I11) -> 0.38
A12: ORD-011 | B12: 2024-04-17 | C12: Chittagong | D12: Karim | E12: Software | F12: Antivirus License | G12: 120 | H12: 2200 | I12: =G12*H12 -> 264000 | J12: =I12*0.28 -> 73920 | K12: =I12-J12 -> 190080 | L12: =IF(I12=0,0,K12/I12) -> 0.72
A13: ORD-012 | B13: 2024-04-25 | C13: Sylhet | D13: Rahim | E13: Accessories | F13: Mouse | G13: 90 | H13: 1500 | I13: =G13*H13 -> 135000 | J13: =I13*0.45 -> 60750 | K13: =I13-J13 -> 74250 | L13: =IF(I13=0,0,K13/I13) -> 0.55
A14: ORD-013 | B14: 2024-05-03 | C14: Dhaka | D14: Nadia | E14: Electronics | F14: Smartphone | G14: 45 | H14: 25000 | I14: =G14*H14 -> 1125000 | J14: =I14*0.62 -> 697500 | K14: =I14-J14 -> 427500 | L14: =IF(I14=0,0,K14/I14) -> 0.38
A15: ORD-014 | B15: 2024-05-19 | C15: Rajshahi | D15: Fatima | E15: Software | F15: Office Suite | G15: 35 | H15: 5500 | I15: =G15*H15 -> 192500 | J15: =I15*0.28 -> 53900 | K15: =I15-J15 -> 138600 | L15: =IF(I15=0,0,K15/I15) -> 0.72
A16: ORD-015 | B16: 2024-05-28 | C16: Chittagong | D16: Karim | E16: Accessories | F16: Headphones | G16: 65 | H16: 3500 | I16: =G16*H16 -> 227500 | J16: =I16*0.45 -> 102375 | K16: =I16-J16 -> 125125 | L16: =IF(I16=0,0,K16/I16) -> 0.55
A17: ORD-016 | B17: 2024-06-04 | C17: Dhaka | D17: Rahim | E17: Electronics | F17: Tablet | G17: 18 | H17: 35000 | I17: =G17*H17 -> 630000 | J17: =I17*0.62 -> 390600 | K17: =I17-J17 -> 239400 | L17: =IF(I17=0,0,K17/I17) -> 0.38
A18: ORD-017 | B18: 2024-06-11 | C18: Sylhet | D18: Nadia | E18: Accessories | F18: USB Hub | G18: 110 | H18: 1200 | I18: =G18*H18 -> 132000 | J18: =I18*0.45 -> 59400 | K18: =I18-J18 -> 72600 | L18: =IF(I18=0,0,K18/I18) -> 0.55
A19: ORD-018 | B19: 2024-06-20 | C19: Rajshahi | D19: Fatima | E19: Electronics | F19: Monitor | G19: 22 | H19: 22000 | I19: =G19*H19 -> 484000 | J19: =I19*0.62 -> 300080 | K19: =I19-J19 -> 183920 | L19: =IF(I19=0,0,K19/I19) -> 0.38
A20: ORD-019 | B20: 2024-07-02 | C20: Dhaka | D20: Karim | E20: Software | F20: Antivirus License | G20: 95 | H20: 2200 | I20: =G20*H20 -> 209000 | J20: =I20*0.28 -> 58520 | K20: =I20-J20 -> 150480 | L20: =IF(I20=0,0,K20/I20) -> 0.72
A21: ORD-020 | B21: 2024-07-14 | C21: Chittagong | D21: Rahim | E21: Electronics | F21: Laptop | G21: 10 | H21: 75000 | I21: =G21*H21 -> 750000 | J21: =I21*0.62 -> 465000 | K21: =I21-J21 -> 285000 | L21: =IF(I21=0,0,K21/I21) -> 0.38
A22: ORD-021 | B22: 2024-07-23 | C22: Sylhet | D22: Nadia | E22: Accessories | F22: Keyboard | G22: 85 | H22: 2800 | I22: =G22*H22 -> 238000 | J22: =I22*0.45 -> 107100 | K22: =I22-J22 -> 130900 | L22: =IF(I22=0,0,K22/I22) -> 0.55
A23: ORD-022 | B23: 2024-08-05 | C23: Dhaka | D23: Fatima | E23: Electronics | F23: Smartphone | G23: 55 | H23: 25000 | I23: =G23*H23 -> 1375000 | J23: =I23*0.62 -> 852500 | K23: =I23-J23 -> 522500 | L23: =IF(I23=0,0,K23/I23) -> 0.38
A24: ORD-023 | B24: 2024-08-18 | C24: Rajshahi | D24: Karim | E24: Software | F24: Office Suite | G24: 40 | H24: 5500 | I24: =G24*H24 -> 220000 | J24: =I24*0.28 -> 61600 | K24: =I24-J24 -> 158400 | L24: =IF(I24=0,0,K24/I24) -> 0.72
A25: ORD-024 | B25: 2024-08-27 | C25: Chittagong | D25: Rahim | E25: Accessories | F25: Mouse | G25: 120 | H25: 1500 | I25: =G25*H25 -> 180000 | J25: =I25*0.45 -> 81000 | K25: =I25-J25 -> 99000 | L25: =IF(I25=0,0,K25/I25) -> 0.55
A26: ORD-025 | B26: 2024-09-06 | C26: Dhaka | D26: Nadia | E26: Electronics | F26: Tablet | G26: 25 | H26: 35000 | I26: =G26*H26 -> 875000 | J26: =I26*0.62 -> 542500 | K26: =I26-J26 -> 332500 | L26: =IF(I26=0,0,K26/I26) -> 0.38
A27: ORD-026 | B27: 2024-09-15 | C27: Sylhet | D27: Fatima | E27: Electronics | F27: Monitor | G27: 18 | H27: 22000 | I27: =G27*H27 -> 396000 | J27: =I27*0.62 -> 245520 | K27: =I27-J27 -> 150480 | L27: =IF(I27=0,0,K27/I27) -> 0.38
A28: ORD-027 | B28: 2024-09-24 | C28: Rajshahi | D28: Karim | E28: Accessories | F28: Headphones | G28: 70 | H28: 3500 | I28: =G28*H28 -> 245000 | J28: =I28*0.45 -> 110250 | K28: =I28-J28 -> 134750 | L28: =IF(I28=0,0,K28/I28) -> 0.55
A29: ORD-028 | B29: 2024-10-07 | C29: Dhaka | D29: Rahim | E29: Software | F29: Antivirus License | G29: 105 | H29: 2200 | I29: =G29*H29 -> 231000 | J29: =I29*0.28 -> 64680 | K29: =I29-J29 -> 166320 | L29: =IF(I29=0,0,K29/I29) -> 0.72
A30: ORD-029 | B30: 2024-10-16 | C30: Chittagong | D30: Nadia | E30: Electronics | F30: Laptop | G30: 14 | H30: 75000 | I30: =G30*H30 -> 1050000 | J30: =I30*0.62 -> 651000 | K30: =I30-J30 -> 399000 | L30: =IF(I30=0,0,K30/I30) -> 0.38
A31: ORD-030 | B31: 2024-10-25 | C31: Sylhet | D31: Fatima | E31: Accessories | F31: USB Hub | G31: 130 | H31: 1200 | I31: =G31*H31 -> 156000 | J31: =I31*0.45 -> 70200 | K31: =I31-J31 -> 85800 | L31: =IF(I31=0,0,K31/I31) -> 0.55
A32: ORD-031 | B32: 2024-11-04 | C32: Dhaka | D32: Karim | E32: Electronics | F32: Smartphone | G32: 60 | H32: 25000 | I32: =G32*H32 -> 1500000 | J32: =I32*0.62 -> 930000 | K32: =I32-J32 -> 570000 | L32: =IF(I32=0,0,K32/I32) -> 0.38
A33: ORD-032 | B33: 2024-11-13 | C33: Rajshahi | D33: Rahim | E33: Software | F33: Office Suite | G33: 50 | H33: 5500 | I33: =G33*H33 -> 275000 | J33: =I33*0.28 -> 77000 | K33: =I33-J33 -> 198000 | L33: =IF(I33=0,0,K33/I33) -> 0.72
A34: ORD-033 | B34: 2024-11-22 | C34: Chittagong | D34: Nadia | E34: Accessories | F34: Keyboard | G34: 95 | H34: 2800 | I34: =G34*H34 -> 266000 | J34: =I34*0.45 -> 119700 | K34: =I34-J34 -> 146300 | L34: =IF(I34=0,0,K34/I34) -> 0.55
A35: ORD-034 | B35: 2024-12-03 | C35: Dhaka | D35: Fatima | E35: Electronics | F35: Tablet | G35: 30 | H35: 35000 | I35: =G35*H35 -> 1050000 | J35: =I35*0.62 -> 651000 | K35: =I35-J35 -> 399000 | L35: =IF(I35=0,0,K35/I35) -> 0.38
A36: ORD-035 | B36: 2024-12-12 | C36: Sylhet | D36: Karim | E36: Electronics | F36: Monitor | G36: 20 | H36: 22000 | I36: =G36*H36 -> 440000 | J36: =I36*0.62 -> 272800 | K36: =I36-J36 -> 167200 | L36: =IF(I36=0,0,K36/I36) -> 0.38
A37: ORD-036 | B37: 2024-12-20 | C37: Rajshahi | D37: Rahim | E37: Accessories | F37: Mouse | G37: 140 | H37: 1500 | I37: =G37*H37 -> 210000 | J37: =I37*0.45 -> 94500 | K37: =I37-J37 -> 115500 | L37: =IF(I37=0,0,K37/I37) -> 0.55

Sheet Lookup Table
A1: PRODUCT LOOKUP & SALESPERSON PERFORMANCE TABLE
A3: Product Name | B3: Category | C3: Unit Price (BDT) | D3: COGS % | E3: Target Units/Month | G3: XLOOKUP / VLOOKUP DEMO
A4: Laptop | B4: Electronics | C4: 75000 | D4: 0.62 | E4: 10 | G4: Lookup Product: | I4: Smartphone
A5: Smartphone | B5: Electronics | C5: 25000 | D5: 0.62 | E5: 40 | G5: Category (XLOOKUP): | I5: =IFERROR(INDEX(B4:B13,MATCH(I4,A4:A13,0)),"Not Found") -> Electronics
A6: Tablet | B6: Electronics | C6: 35000 | D6: 0.62 | E6: 20 | G6: Unit Price (VLOOKUP): | I6: =VLOOKUP(I4,A4:C13,3,FALSE()) -> 25000
A7: Monitor | B7: Electronics | C7: 22000 | D7: 0.62 | E7: 15 | G7: COGS % (XLOOKUP): | I7: =IFERROR(INDEX(D4:D13,MATCH(I4,A4:A13,0)),"Not Found") -> 0.62
A8: Headphones | B8: Accessories | C8: 3500 | D8: 0.45 | E8: 60 | G8: Target Units (HLOOKUP): | I8: =HLOOKUP(I4,A16:J17,2,FALSE()) -> 40
A9: USB Hub | B9: Accessories | C9: 1200 | D9: 0.45 | E9: 100
A10: Keyboard | B10: Accessories | C10: 2800 | D10: 0.45 | E10: 80
A11: Mouse | B11: Accessories | C11: 1500 | D11: 0.45 | E11: 90
A12: Antivirus License | B12: Software | C12: 2200 | D12: 0.28 | E12: 100
A13: Office Suite | B13: Software | C13: 5500 | D13: 0.28 | E13: 50
A15: HLOOKUP SOURCE TABLE (Horizontal Layout — Monthly Targets)
A16: Laptop | B16: Smartphone | C16: Tablet | D16: Monitor | E16: Headphones | F16: USB Hub | G16: Keyboard | H16: Mouse | I16: Antivirus License | J16: Office Suite
A17: 10 | B17: 40 | C17: 20 | D17: 15 | E17: 60 | F17: 100 | G17: 80 | H17: 90 | I17: 100 | J17: 50

Sheet Pivot Summary
A1: SALES PIVOT SUMMARY — FY 2024
A3: Revenue by Product Category | G3: Revenue by Region
A4: Category | B4: Total Revenue | C4: Total Units | D4: Avg Margin | E4: % of Total | G4: Region | H4: Total Revenue | I4: Total Units | J4: Best Month | K4: Avg Deal Size
A5: Electronics | B5: ='Raw Data'!I2+'Raw Data'!I3+'Raw Data'!I6+'Raw Data'!I9+'Raw Data'!I11+'Raw Data'!I14+'Raw Data'!I17+'Raw Data'!I19+'Raw Data'!I21+'Raw Data'!I23+'Raw Data'!I26+'Raw Data'!I27+'Raw Data'!I30+'Raw Data'!I32+'Raw Data'!I35+'Raw Data'!I36 -> 12955000 | C5: ='Raw Data'!G2+'Raw Data'!G3+'Raw Data'!G6+'Raw Data'!G9+'Raw Data'!G11+'Raw Data'!G14+'Raw Data'!G17+'Raw Data'!G19+'Raw Data'!G21+'Raw Data'!G23+'Raw Data'!G26+'Raw Data'!G27+'Raw Data'!G30+'Raw Data'!G32+'Raw Data'!G35+'Raw Data'!G36 -> 402 | D5: =AVERAGEIF('Raw Data'!E2:E37,A5,'Raw Data'!L2:L37) -> 0.38 | E5: =B5/SUM(B5:B7) -> 0.75552575 | G5: Dhaka | H5: =SUMIF('Raw Data'!C2:C37,G5,'Raw Data'!I2:I37) -> 9001000 | I5: =SUMIF('Raw Data'!C2:C37,G5,'Raw Data'!G2:G37) -> 593 | J5: See Dashboard | K5: =IFERROR(H5/I5,0) -> 15178.752
A6: Software | B6: ='Raw Data'!I5+'Raw Data'!I8+'Raw Data'!I12+'Raw Data'!I15+'Raw Data'!I20+'Raw Data'!I24+'Raw Data'!I29+'Raw Data'!I33 -> 1897500 | C6: ='Raw Data'!G5+'Raw Data'!G8+'Raw Data'!G12+'Raw Data'!G15+'Raw Data'!G20+'Raw Data'!G24+'Raw Data'!G29+'Raw Data'!G33 -> 585 | D6: =AVERAGEIF('Raw Data'!E2:E37,A6,'Raw Data'!L2:L37) -> 0.72 | E6: =B6/SUM(B5:B7) -> 0.11066076 | G6: Chittagong | H6: =SUMIF('Raw Data'!C2:C37,G6,'Raw Data'!I2:I37) -> 3607500 | I6: =SUMIF('Raw Data'!C2:C37,G6,'Raw Data'!G2:G37) -> 554 | J6: See Dashboard | K6: =IFERROR(H6/I6,0) -> 6511.7329
A7: Accessories | B7: ='Raw Data'!I4+'Raw Data'!I7+'Raw Data'!I10+'Raw Data'!I13+'Raw Data'!I16+'Raw Data'!I18+'Raw Data'!I22+'Raw Data'!I25+'Raw Data'!I28+'Raw Data'!I31+'Raw Data'!I34+'Raw Data'!I37 -> 2294500 | C7: ='Raw Data'!G4+'Raw Data'!G7+'Raw Data'!G10+'Raw Data'!G13+'Raw Data'!G16+'Raw Data'!G18+'Raw Data'!G22+'Raw Data'!G25+'Raw Data'!G28+'Raw Data'!G31+'Raw Data'!G34+'Raw Data'!G37 -> 1130 | D7: =AVERAGEIF('Raw Data'!E2:E37,A7,'Raw Data'!L2:L37) -> 0.55 | E7: =B7/SUM(B5:B7) -> 0.1338135 | G7: Sylhet | H7: =SUMIF('Raw Data'!C2:C37,G7,'Raw Data'!I2:I37) -> 2002000 | I7: =SUMIF('Raw Data'!C2:C37,G7,'Raw Data'!G2:G37) -> 518 | J7: See Dashboard | K7: =IFERROR(H7/I7,0) -> 3864.8649
A8: TOTAL | B8: =SUM(B5:B7) -> 17147000 | C8: =SUM(C5:C7) -> 2117 | G8: Rajshahi | H8: =SUMIF('Raw Data'!C2:C37,G8,'Raw Data'!I2:I37) -> 2536500 | I8: =SUMIF('Raw Data'!C2:C37,G8,'Raw Data'!G2:G37) -> 452 | J8: See Dashboard | K8: =IFERROR(H8/I8,0) -> 5611.7257
G9: TOTAL | H9: =SUM(H5:H8) -> 17147000 | I9: =SUM(I5:I8) -> 2117
A11: Salesperson Performance
A12: Salesperson | B12: Total Revenue | C12: Total Units | D12: Avg Margin | E12: Rank
A13: Rahim | B13: =SUMIF('Raw Data'!D2:D37,A13,'Raw Data'!I2:I37) -> 3817000 | C13: =SUMIF('Raw Data'!D2:D37,A13,'Raw Data'!G2:G37) -> 640 | D13: =AVERAGEIF('Raw Data'!D2:D37,A13,'Raw Data'!L2:L37) -> 0.533 | E13: =RANK(B13,B13:B16,0) -> 3
A14: Fatima | B14: =SUMIF('Raw Data'!D2:D37,A14,'Raw Data'!I2:I37) -> 5123500 | C14: =SUMIF('Raw Data'!D2:D37,A14,'Raw Data'!G2:G37) -> 428 | D14: =AVERAGEIF('Raw Data'!D2:D37,A14,'Raw Data'!L2:L37) -> 0.45555556 | E14: =RANK(B14,B13:B16,0) -> 1
A15: Karim | B15: =SUMIF('Raw Data'!D2:D37,A15,'Raw Data'!I2:I37) -> 3610500 | C15: =SUMIF('Raw Data'!D2:D37,A15,'Raw Data'!G2:G37) -> 580 | D15: =AVERAGEIF('Raw Data'!D2:D37,A15,'Raw Data'!L2:L37) -> 0.58777778 | E15: =RANK(B15,B13:B16,0) -> 4
A16: Nadia | B16: =SUMIF('Raw Data'!D2:D37,A16,'Raw Data'!I2:I37) -> 4596000 | C16: =SUMIF('Raw Data'!D2:D37,A16,'Raw Data'!G2:G37) -> 469 | D16: =AVERAGEIF('Raw Data'!D2:D37,A16,'Raw Data'!L2:L37) -> 0.465 | E16: =RANK(B16,B13:B16,0) -> 2

Sheet Monthly Trend
A1: MONTHLY REVENUE & PROFIT TREND — FY 2024
A3: Month | B3: Revenue (BDT) | C3: Gross Profit (BDT) | D3: Units Sold | E3: Profit Margin (%) | F3: MoM Growth (%) | G3: Target Revenue
A4: Jan | B4: ='Raw Data'!I2+'Raw Data'!I3+'Raw Data'!I4 -> 1825000 | C4: ='Raw Data'!K2+'Raw Data'!K3+'Raw Data'!K4 -> 723250 | D4: ='Raw Data'!G2+'Raw Data'!G3+'Raw Data'!G4 -> 92 | E4: =IFERROR(C4/B4,0) -> 0.39630137 | F4: - | G4: 3500000
A5: Feb | B5: ='Raw Data'!I5+'Raw Data'!I6+'Raw Data'!I7 -> 996000 | C5: ='Raw Data'!K5+'Raw Data'!K6+'Raw Data'!K7 -> 458720 | D5: ='Raw Data'!G5+'Raw Data'!G6+'Raw Data'!G7 -> 200 | E5: =IFERROR(C5/B5,0) -> 0.46056225 | F5: =IFERROR((B5-B4)/B4,0) -> -0.45424658 | G5: 3800000
A6: Mar | B6: ='Raw Data'!I8+'Raw Data'!I9+'Raw Data'!I10 -> 870000 | C6: ='Raw Data'!K8+'Raw Data'!K9+'Raw Data'!K10 -> 478500 | D6: ='Raw Data'!G8+'Raw Data'!G9+'Raw Data'!G10 -> 150 | E6: =IFERROR(C6/B6,0) -> 0.55 | F6: =IFERROR((B6-B5)/B5,0) -> -0.12650602 | G6: 4000000
A7: Apr | B7: ='Raw Data'!I11+'Raw Data'!I12+'Raw Data'!I13 -> 999000 | C7: ='Raw Data'!K11+'Raw Data'!K12+'Raw Data'!K13 -> 492330 | D7: ='Raw Data'!G11+'Raw Data'!G12+'Raw Data'!G13 -> 218 | E7: =IFERROR(C7/B7,0) -> 0.49282282 | F7: =IFERROR((B7-B6)/B6,0) -> 0.14827586 | G7: 4200000
A8: May | B8: ='Raw Data'!I14+'Raw Data'!I15+'Raw Data'!I16 -> 1545000 | C8: ='Raw Data'!K14+'Raw Data'!K15+'Raw Data'!K16 -> 691225 | D8: ='Raw Data'!G14+'Raw Data'!G15+'Raw Data'!G16 -> 145 | E8: =IFERROR(C8/B8,0) -> 0.44739482 | F8: =IFERROR((B8-B7)/B7,0) -> 0.54654655 | G8: 4500000
A9: Jun | B9: ='Raw Data'!I17+'Raw Data'!I18+'Raw Data'!I19 -> 1246000 | C9: ='Raw Data'!K17+'Raw Data'!K18+'Raw Data'!K19 -> 495920 | D9: ='Raw Data'!G17+'Raw Data'!G18+'Raw Data'!G19 -> 150 | E9: =IFERROR(C9/B9,0) -> 0.39800963 | F9: =IFERROR((B9-B8)/B8,0) -> -0.19352751 | G9: 4800000
A10: Jul | B10: ='Raw Data'!I20+'Raw Data'!I21+'Raw Data'!I22 -> 1197000 | C10: ='Raw Data'!K20+'Raw Data'!K21+'Raw Data'!K22 -> 566380 | D10: ='Raw Data'!G20+'Raw Data'!G21+'Raw Data'!G22 -> 190 | E10: =IFERROR(C10/B10,0) -> 0.47316625 | F10: =IFERROR((B10-B9)/B9,0) -> -0.039325843 | G10: 5000000
A11: Aug | B11: ='Raw Data'!I23+'Raw Data'!I24+'Raw Data'!I25 -> 1775000 | C11: ='Raw Data'!K23+'Raw Data'!K24+'Raw Data'!K25 -> 779900 | D11: ='Raw Data'!G23+'Raw Data'!G24+'Raw Data'!G25 -> 215 | E11: =IFERROR(C11/B11,0) -> 0.43938028 | F11: =IFERROR((B11-B10)/B10,0) -> 0.48287385 | G11: 5200000
A12: Sep | B12: ='Raw Data'!I26+'Raw Data'!I27+'Raw Data'!I28 -> 1516000 | C12: ='Raw Data'!K26+'Raw Data'!K27+'Raw Data'!K28 -> 617730 | D12: ='Raw Data'!G26+'Raw Data'!G27+'Raw Data'!G28 -> 113 | E12: =IFERROR(C12/B12,0) -> 0.40747361 | F12: =IFERROR((B12-B11)/B11,0) -> -0.14591549 | G12: 5500000
A13: Oct | B13: ='Raw Data'!I29+'Raw Data'!I30+'Raw Data'!I31 -> 1437000 | C13: ='Raw Data'!K29+'Raw Data'!K30+'Raw Data'!K31 -> 651120 | D13: ='Raw Data'!G29+'Raw Data'!G30+'Raw Data'!G31 -> 249 | E13: =IFERROR(C13/B13,0) -> 0.45311065 | F13: =IFERROR((B13-B12)/B12,0) -> -0.052110818 | G13: 5800000
A14: Nov | B14: ='Raw Data'!I32+'Raw Data'!I33+'Raw Data'!I34 -> 2041000 | C14: ='Raw Data'!K32+'Raw Data'!K33+'Raw Data'!K34 -> 914300 | D14: ='Raw Data'!G32+'Raw Data'!G33+'Raw Data'!G34 -> 205 | E14: =IFERROR(C14/B14,0) -> 0.44796668 | F14: =IFERROR((B14-B13)/B13,0) -> 0.42032011 | G14: 6000000
A15: Dec | B15: ='Raw Data'!I35+'Raw Data'!I36+'Raw Data'!I37 -> 1700000 | C15: ='Raw Data'!K35+'Raw Data'!K36+'Raw Data'!K37 -> 681700 | D15: ='Raw Data'!G35+'Raw Data'!G36+'Raw Data'!G37 -> 190 | E15: =IFERROR(C15/B15,0) -> 0.401 | F15: =IFERROR((B15-B14)/B14,0) -> -0.16707496 | G15: 6500000

Sheet What-If Analysis
A1: WHAT-IF ANALYSIS — REVENUE SCENARIO PLANNER
A3: INPUT ASSUMPTIONS (blue = change these)
A4: Base Units Sold / Month | C4: 85
A5: Average Unit Price (BDT) | C5: 18500
A6: Expected Growth Rate / Month | C6: 0.03
A7: COGS as % of Revenue | C7: 0.52
A8: Target Profit Margin | C8: 0.3
A10: 12-MONTH REVENUE PROJECTION (formula-driven from assumptions above)
A11: Month | B11: Projected Units | C11: Unit Price | D11: Revenue | E11: COGS | F11: Gross Profit | G11: Margin | H11: vs Target
A12: Jan | B12: =$C$4 -> 85 | C12: =$C$5 -> 18500 | D12: =B12*C12 -> 1572500 | E12: =D12*$C$7 -> 817700 | F12: =D12-E12 -> 754800 | G12: =IFERROR(F12/D12,0) -> 0.48 | H12: =IF(G12>=$C$8,"On Track","Below Target") -> On Track
A13: Feb | B13: =ROUND(B12*(1+$C$6),0) -> 88 | C13: =$C$5 -> 18500 | D13: =B13*C13 -> 1628000 | E13: =D13*$C$7 -> 846560 | F13: =D13-E13 -> 781440 | G13: =IFERROR(F13/D13,0) -> 0.48 | H13: =IF(G13>=$C$8,"On Track","Below Target") -> On Track
A14: Mar | B14: =ROUND(B13*(1+$C$6),0) -> 91 | C14: =$C$5 -> 18500 | D14: =B14*C14 -> 1683500 | E14: =D14*$C$7 -> 875420 | F14: =D14-E14 -> 808080 | G14: =IFERROR(F14/D14,0) -> 0.48 | H14: =IF(G14>=$C$8,"On Track","Below Target") -> On Track
A15: Apr | B15: =ROUND(B14*(1+$C$6),0) -> 94 | C15: =$C$5 -> 18500 | D15: =B15*C15 -> 1739000 | E15: =D15*$C$7 -> 904280 | F15: =D15-E15 -> 834720 | G15: =IFERROR(F15/D15,0) -> 0.48 | H15: =IF(G15>=$C$8,"On Track","Below Target") -> On Track
A16: May | B16: =ROUND(B15*(1+$C$6),0) -> 97 | C16: =$C$5 -> 18500 | D16: =B16*C16 -> 1794500 | E16: =D16*$C$7 -> 933140 | F16: =D16-E16 -> 861360 | G16: =IFERROR(F16/D16,0) -> 0.48 | H16: =IF(G16>=$C$8,"On Track","Below Target") -> On Track
A17: Jun | B17: =ROUND(B16*(1+$C$6),0) -> 100 | C17: =$C$5 -> 18500 | D17: =B17*C17 -> 1850000 | E17: =D17*$C$7 -> 962000 | F17: =D17-E17 -> 888000 | G17: =IFERROR(F17/D17,0) -> 0.48 | H17: =IF(G17>=$C$8,"On Track","Below Target") -> On Track
A18: Jul | B18: =ROUND(B17*(1+$C$6),0) -> 103 | C18: =$C$5 -> 18500 | D18: =B18*C18 -> 1905500 | E18: =D18*$C$7 -> 990860 | F18: =D18-E18 -> 914640 | G18: =IFERROR(F18/D18,0) -> 0.48 | H18: =IF(G18>=$C$8,"On Track","Below Target") -> On Track
A19: Aug | B19: =ROUND(B18*(1+$C$6),0) -> 106 | C19: =$C$5 -> 18500 | D19: =B19*C19 -> 1961000 | E19: =D19*$C$7 -> 1019720 | F19: =D19-E19 -> 941280 | G19: =IFERROR(F19/D19,0) -> 0.48 | H19: =IF(G19>=$C$8,"On Track","Below Target") -> On Track
A20: Sep | B20: =ROUND(B19*(1+$C$6),0) -> 109 | C20: =$C$5 -> 18500 | D20: =B20*C20 -> 2016500 | E20: =D20*$C$7 -> 1048580 | F20: =D20-E20 -> 967920 | G20: =IFERROR(F20/D20,0) -> 0.48 | H20: =IF(G20>=$C$8,"On Track","Below Target") -> On Track
A21: Oct | B21: =ROUND(B20*(1+$C$6),0) -> 112 | C21: =$C$5 -> 18500 | D21: =B21*C21 -> 2072000 | E21: =D21*$C$7 -> 1077440 | F21: =D21-E21 -> 994560 | G21: =IFERROR(F21/D21,0) -> 0.48 | H21: =IF(G21>=$C$8,"On Track","Below Target") -> On Track
A22: Nov | B22: =ROUND(B21*(1+$C$6),0) -> 115 | C22: =$C$5 -> 18500 | D22: =B22*C22 -> 2127500 | E22: =D22*$C$7 -> 1106300 | F22: =D22-E22 -> 1021200 | G22: =IFERROR(F22/D22,0) -> 0.48 | H22: =IF(G22>=$C$8,"On Track","Below Target") -> On Track
A23: Dec | B23: =ROUND(B22*(1+$C$6),0) -> 118 | C23: =$C$5 -> 18500 | D23: =B23*C23 -> 2183000 | E23: =D23*$C$7 -> 1135160 | F23: =D23-E23 -> 1047840 | G23: =IFERROR(F23/D23,0) -> 0.48 | H23: =IF(G23>=$C$8,"On Track","Below Target") -> On Track
A25: SCENARIO SUMMARY KPIs
A26: Total Projected Revenue (BDT) | C26: =SUM(D12:D23) -> 22533000
A27: Total Gross Profit (BDT) | C27: =SUM(F12:F23) -> 10815840
A28: Average Monthly Margin | C28: =AVERAGE(G12:G23) -> 0.48
A29: Months On Track | C29: =COUNTIF(H12:H23,"On Track") -> 12

Sheet Dashboard
B2: SALES & REVENUE ANALYSIS DASHBOARD — FY 2024
B4: Total Revenue | D4: Total Gross Profit | F4: Total Units Sold | H4: Avg Profit Margin | J4: Top Salesperson
B6: ='Pivot Summary'!B8 -> 17147000 | D6: ='Pivot Summary'!B8*AVERAGE('Raw Data'!L2:L37) -> 8783074.4 | F6: ='Pivot Summary'!C8 -> 2117 | H6: =AVERAGE('Raw Data'!L2:L37) -> 0.51222222 | J6: =INDEX('Pivot Summary'!A13:A16,MATCH(MAX('Pivot Summary'!B13:B16),'Pivot Summary'!B13:B16,0)) -> Fatima
B8: This Dashboard auto-updates from Raw Data, Pivot Summary, and Monthly Trend sheets. Refresh PivotTables (Data → Refresh All) after adding new rows to Raw Data. Use the What-If Analysis sheet to model revenue scenarios.
B10: Quick KPI Summary (Linked from Pivot Summary) | I10: Salesperson Ranking
B11: Category | C11: Revenue | D11: Units | E11: Margin | I11: Name | J11: Revenue | K11: Rank
B12: Electronics | C12: ='Pivot Summary'!B5 -> 12955000 | D12: ='Pivot Summary'!C5 -> 402 | E12: ='Pivot Summary'!D5 -> 0.38 | I12: Rahim | J12: ='Pivot Summary'!B10 -> 0 | K12: ='Pivot Summary'!E10 -> 0
B13: Software | C13: ='Pivot Summary'!B6 -> 1897500 | D13: ='Pivot Summary'!C6 -> 585 | E13: ='Pivot Summary'!D6 -> 0.72 | I13: Fatima | J13: ='Pivot Summary'!B11 -> 0 | K13: ='Pivot Summary'!E11 -> 0
B14: Accessories | C14: ='Pivot Summary'!B7 -> 2294500 | D14: ='Pivot Summary'!C7 -> 1130 | E14: ='Pivot Summary'!D7 -> 0.55 | I14: Karim | J14: ='Pivot Summary'!B12 -> Total Revenue | K14: ='Pivot Summary'!E12 -> Rank
I15: Nadia | J15: ='Pivot Summary'!B13 -> 3817000 | K15: ='Pivot Summary'!E13 -> 3
